YehuoIMxLinuxKaifaShizhanZhinan/README.md
YehuoIMxLinuxKaifaShizhanZhinan/__init__.py
YehuoIMxLinuxKaifaShizhanZhinan/__main__.py
YehuoIMxLinuxKaifaShizhanZhinan/file.epub
YehuoIMxLinuxKaifaShizhanZhinan/index.html
YehuoIMxLinuxKaifaShizhanZhinan/css/__init__.py
YehuoIMxLinuxKaifaShizhanZhinan/css/annotations.css
YehuoIMxLinuxKaifaShizhanZhinan/css/main.css
YehuoIMxLinuxKaifaShizhanZhinan/css/normalize.css
YehuoIMxLinuxKaifaShizhanZhinan/css/popup.css
YehuoIMxLinuxKaifaShizhanZhinan/font/__init__.py
YehuoIMxLinuxKaifaShizhanZhinan/font/fontello.eot
YehuoIMxLinuxKaifaShizhanZhinan/font/fontello.svg
YehuoIMxLinuxKaifaShizhanZhinan/font/fontello.ttf
YehuoIMxLinuxKaifaShizhanZhinan/font/fontello.woff
YehuoIMxLinuxKaifaShizhanZhinan/img/__init__.py
YehuoIMxLinuxKaifaShizhanZhinan/img/annotator-glyph-sprite.png
YehuoIMxLinuxKaifaShizhanZhinan/img/annotator-icon-sprite.png
YehuoIMxLinuxKaifaShizhanZhinan/img/apple-touch-icon.png
YehuoIMxLinuxKaifaShizhanZhinan/img/cancelfullscreen.png
YehuoIMxLinuxKaifaShizhanZhinan/img/close.png
YehuoIMxLinuxKaifaShizhanZhinan/img/fullscreen.png
YehuoIMxLinuxKaifaShizhanZhinan/img/loader.gif
YehuoIMxLinuxKaifaShizhanZhinan/img/menu-icon.png
YehuoIMxLinuxKaifaShizhanZhinan/img/save.png
YehuoIMxLinuxKaifaShizhanZhinan/img/saved.png
YehuoIMxLinuxKaifaShizhanZhinan/img/settings-s.png
YehuoIMxLinuxKaifaShizhanZhinan/img/settings.png
YehuoIMxLinuxKaifaShizhanZhinan/img/star.png
YehuoIMxLinuxKaifaShizhanZhinan/js/__init__.py
YehuoIMxLinuxKaifaShizhanZhinan/js/epub.js
YehuoIMxLinuxKaifaShizhanZhinan/js/epub.min.js
YehuoIMxLinuxKaifaShizhanZhinan/js/epub.min.map
YehuoIMxLinuxKaifaShizhanZhinan/js/hooks.min.js
YehuoIMxLinuxKaifaShizhanZhinan/js/hooks.min.map
YehuoIMxLinuxKaifaShizhanZhinan/js/reader.js
YehuoIMxLinuxKaifaShizhanZhinan/js/reader.js.map
YehuoIMxLinuxKaifaShizhanZhinan/js/reader.min.js
YehuoIMxLinuxKaifaShizhanZhinan/js/reader.min.map
YehuoIMxLinuxKaifaShizhanZhinan/js/hooks/__init__.py
yehuo_i_mx_linux_kaifa_shizhan_zhinan-2024.3.5.0.dist-info/METADATA
yehuo_i_mx_linux_kaifa_shizhan_zhinan-2024.3.5.0.dist-info/WHEEL
yehuo_i_mx_linux_kaifa_shizhan_zhinan-2024.3.5.0.dist-info/entry_points.txt
yehuo_i_mx_linux_kaifa_shizhan_zhinan-2024.3.5.0.dist-info/top_level.txt
yehuo_i_mx_linux_kaifa_shizhan_zhinan-2024.3.5.0.dist-info/RECORD
